frotech_adapter/__init__.py
frotech_adapter/airPump.py
frotech_adapter/car.py
frotech_adapter/claw.py
frotech_adapter/config.py
frotech_adapter/dummyArm.py
frotech_adapter/enc_car.py
frotech_adapter/heartbeat.py
frotech_adapter/ledMatrix.py
frotech_adapter/lift.py
frotech_adapter/lobotArm.py
frotech_adapter/lobotServo.py
frotech_adapter/motor.py
frotech_adapter/pantilt.py
frotech_adapter/piece.py
frotech_adapter/powerDetect.py
frotech_adapter/robotServo.py
frotech_adapter/serialLed.py
frotech_adapter/serialServo.py
frotech_adapter/servo.py
frotech_adapter/speechRec.py
frotech_adapter/utils.py
jetson_adapter_pkg-0.13.4.dist-info/LICENSE
jetson_adapter_pkg-0.13.4.dist-info/METADATA
jetson_adapter_pkg-0.13.4.dist-info/WHEEL
jetson_adapter_pkg-0.13.4.dist-info/top_level.txt
jetson_adapter_pkg-0.13.4.dist-info/RECORD
