Metadata-Version: 2.1
Name: jetson-adapter-pkg
Version: 0.13.4
Summary: A package for aiotlab adapter control
Home-page: https://gitee.com/z14git/aiotlab_jetson_adapter
Author: z14git
Author-email: lzl1992@gmail.com
Classifier: Programming Language :: Python :: 3
Classifier: License :: OSI Approved :: MIT License
Classifier: Operating System :: OS Independent
Requires-Python: >=3.6
License-File: LICENSE
Requires-Dist: modbus-tk
Requires-Dist: crcmod
Requires-Dist: traitlets
Provides-Extra: heartbeat
Requires-Dist: ipywidgets ; extra == 'heartbeat'
